{
  "id": "ddd21c0e-3fed-4be3-9500-56fca33a65aa",
  "prevId": "00000000-0000-0000-0000-000000000000",
  "version": "7",
  "dialect": "postgresql",
  "tables": {
    "public.images": {
      "name": "images",
      "schema": "",
      "columns": {
        "id": {
          "name": "id",
          "type": "uuid",
          "primaryKey": true,
          "notNull": true,
          "default": "gen_random_uuid()"
        },
        "path": {
          "name": "path",
          "type": "text",
          "primaryKey": false,
          "notNull": true
        },
        "filename": {
          "name": "filename",
          "type": "text",
          "primaryKey": false,
          "notNull": true
        },
        "page": {
          "name": "page",
          "type": "integer",
          "primaryKey": false,
          "notNull": false
        },
        "title": {
          "name": "title",
          "type": "text",
          "primaryKey": false,
          "notNull": false
        },
        "author": {
          "name": "author",
          "type": "text",
          "primaryKey": false,
          "notNull": false
        },
        "size": {
          "name": "size",
          "type": "integer",
          "primaryKey": false,
          "notNull": false
        },
        "last_modified": {
          "name": "last_modified",
          "type": "timestamp",
          "primaryKey": false,
          "notNull": false
        },
        "is_page_based": {
          "name": "is_page_based",
          "type": "integer",
          "primaryKey": false,
          "notNull": false,
          "default": 0
        },
        "section_title": {
          "name": "section_title",
          "type": "text",
          "primaryKey": false,
          "notNull": false
        },
        "section_page": {
          "name": "section_page",
          "type": "integer",
          "primaryKey": false,
          "notNull": false
        },
        "photo_number": {
          "name": "photo_number",
          "type": "integer",
          "primaryKey": false,
          "notNull": false
        },
        "created_at": {
          "name": "created_at",
          "type": "timestamp",
          "primaryKey": false,
          "notNull": false,
          "default": "now()"
        }
      },
      "indexes": {},
      "foreignKeys": {},
      "compositePrimaryKeys": {},
      "uniqueConstraints": {
        "images_path_unique": {
          "name": "images_path_unique",
          "nullsNotDistinct": false,
          "columns": [
            "path"
          ]
        }
      },
      "policies": {},
      "checkConstraints": {},
      "isRLSEnabled": false
    },
    "public.testimonies": {
      "name": "testimonies",
      "schema": "",
      "columns": {
        "id": {
          "name": "id",
          "type": "text",
          "primaryKey": true,
          "notNull": true
        },
        "title": {
          "name": "title",
          "type": "text",
          "primaryKey": false,
          "notNull": true
        },
        "author": {
          "name": "author",
          "type": "text",
          "primaryKey": false,
          "notNull": true
        },
        "relationship": {
          "name": "relationship",
          "type": "text",
          "primaryKey": false,
          "notNull": true
        },
        "content": {
          "name": "content",
          "type": "text",
          "primaryKey": false,
          "notNull": true
        },
        "page": {
          "name": "page",
          "type": "integer",
          "primaryKey": false,
          "notNull": true
        },
        "category": {
          "name": "category",
          "type": "text",
          "primaryKey": false,
          "notNull": true
        },
        "chapter": {
          "name": "chapter",
          "type": "text",
          "primaryKey": false,
          "notNull": true
        },
        "tags": {
          "name": "tags",
          "type": "jsonb",
          "primaryKey": false,
          "notNull": false,
          "default": "'[]'::jsonb"
        },
        "page_range": {
          "name": "page_range",
          "type": "jsonb",
          "primaryKey": false,
          "notNull": false
        },
        "created_at": {
          "name": "created_at",
          "type": "timestamp",
          "primaryKey": false,
          "notNull": false,
          "default": "now()"
        },
        "updated_at": {
          "name": "updated_at",
          "type": "timestamp",
          "primaryKey": false,
          "notNull": false,
          "default": "now()"
        }
      },
      "indexes": {},
      "foreignKeys": {},
      "compositePrimaryKeys": {},
      "uniqueConstraints": {},
      "policies": {},
      "checkConstraints": {},
      "isRLSEnabled": false
    },
    "public.testimony_images": {
      "name": "testimony_images",
      "schema": "",
      "columns": {
        "testimony_id": {
          "name": "testimony_id",
          "type": "text",
          "primaryKey": false,
          "notNull": false
        },
        "image_id": {
          "name": "image_id",
          "type": "uuid",
          "primaryKey": false,
          "notNull": false
        },
        "caption": {
          "name": "caption",
          "type": "text",
          "primaryKey": false,
          "notNull": false
        },
        "order": {
          "name": "order",
          "type": "integer",
          "primaryKey": false,
          "notNull": false,
          "default": 0
        },
        "created_at": {
          "name": "created_at",
          "type": "timestamp",
          "primaryKey": false,
          "notNull": false,
          "default": "now()"
        }
      },
      "indexes": {},
      "foreignKeys": {
        "testimony_images_testimony_id_testimonies_id_fk": {
          "name": "testimony_images_testimony_id_testimonies_id_fk",
          "tableFrom": "testimony_images",
          "tableTo": "testimonies",
          "columnsFrom": [
            "testimony_id"
          ],
          "columnsTo": [
            "id"
          ],
          "onDelete": "cascade",
          "onUpdate": "no action"
        },
        "testimony_images_image_id_images_id_fk": {
          "name": "testimony_images_image_id_images_id_fk",
          "tableFrom": "testimony_images",
          "tableTo": "images",
          "columnsFrom": [
            "image_id"
          ],
          "columnsTo": [
            "id"
          ],
          "onDelete": "cascade",
          "onUpdate": "no action"
        }
      },
      "compositePrimaryKeys": {
        "testimony_images_testimony_id_image_id_pk": {
          "name": "testimony_images_testimony_id_image_id_pk",
          "columns": [
            "testimony_id",
            "image_id"
          ]
        }
      },
      "uniqueConstraints": {},
      "policies": {},
      "checkConstraints": {},
      "isRLSEnabled": false
    }
  },
  "enums": {},
  "schemas": {},
  "sequences": {},
  "roles": {},
  "policies": {},
  "views": {},
  "_meta": {
    "columns": {},
    "schemas": {},
    "tables": {}
  }
}